aisi/__init__.py
aisi/main.py
aisi/__system__/imports.py
aisi/__system__/index.py
aisi/__system__/modules/jobs.py
aisi/__system__/sources/clight.json
aisi-1.0.0.dist-info/METADATA
aisi-1.0.0.dist-info/WHEEL
aisi-1.0.0.dist-info/entry_points.txt
aisi-1.0.0.dist-info/top_level.txt
aisi-1.0.0.dist-info/RECORD
